dchunk/__init__.py
dchunk/chunking.py
dchunk/tests.py
dchunk-0.0.1.dist-info/LICENSE
dchunk-0.0.1.dist-info/METADATA
dchunk-0.0.1.dist-info/WHEEL
dchunk-0.0.1.dist-info/top_level.txt
dchunk-0.0.1.dist-info/RECORD
